rest_encrypt/__init__.py
rest_encrypt/cli.py
rest_encrypt/crypto.py
rest_encrypt/errors.py
rest_encrypt/keywrap.py
rest_encrypt/store.py
rest_encrypt/platforms/__init__.py
rest_encrypt/platforms/linux.py
rest_encrypt/platforms/windows.py
rest_encrypt/serializers/__init__.py
rest_encrypt/serializers/dict_serializer.py
rest_encrypt/serializers/env_serializer.py
rest_encrypt/serializers/ini_serializer.py
rest_encrypt/serializers/json_serializer.py
rest_encrypt/serializers/toml_serializer.py
rest_encrypt-0.1.0.dist-info/licenses/LICENSE
rest_encrypt-0.1.0.dist-info/METADATA
rest_encrypt-0.1.0.dist-info/WHEEL
rest_encrypt-0.1.0.dist-info/entry_points.txt
rest_encrypt-0.1.0.dist-info/top_level.txt
rest_encrypt-0.1.0.dist-info/RECORD
