Metadata-Version: 2.4
Name: rest-encrypt
Version: 0.1.0
Summary: Lightweight encryption-at-rest for application secrets
License-Expression: Apache-2.0
Keywords: Encrypt at rest
Requires-Python: >=3.11
License-File: LICENSE
Requires-Dist: cryptography>=42.0.0
Requires-Dist: pywin32>=306; sys_platform == "win32"
Requires-Dist: python-dotenv>=1.0.1
Requires-Dist: tomli>=2.0.1; python_version < "3.11"
Requires-Dist: tomli-w>=1.2.0
Dynamic: license-file
